odevio/__init__.py
odevio/__main__.py
odevio/api.py
odevio/helpers.py
odevio/settings.py
odevio/commands/__init__.py
odevio/commands/app.py
odevio/commands/apple.py
odevio/commands/build.py
odevio/commands/team.py
odevio/commands/user.py
odevio-1.2.2.dist-info/METADATA
odevio-1.2.2.dist-info/WHEEL
odevio-1.2.2.dist-info/entry_points.txt
odevio-1.2.2.dist-info/licenses/LICENSE
odevio-1.2.2.dist-info/RECORD
